rhythmdbctl/__init__.py
rhythmdbctl/__main__.py
rhythmdbctl/database.py
rhythmdbctl/formatters.py
rhythmdbctl/models.py
rhythmdbctl-0.1.0.dist-info/LICENSE
rhythmdbctl-0.1.0.dist-info/METADATA
rhythmdbctl-0.1.0.dist-info/WHEEL
rhythmdbctl-0.1.0.dist-info/entry_points.txt
rhythmdbctl-0.1.0.dist-info/RECORD
