Metadata-Version: 2.3
Name: rhythmdbctl
Version: 0.1.0
Summary: rhythmdbctl is a CLI tool to access and control Rhythm DB
License: GPL-3.0-only
Keywords: rhythmbox,music,database,cli,xml
Author: thaim
Author-email: thaim24@gmail.com
Requires-Python: >=3.10,<4.0
Classifier: Development Status :: 3 - Alpha
Classifier: Environment :: Console
Classifier: Intended Audience :: End Users/Desktop
Classifier: License :: OSI Approved :: GNU General Public License v3 (GPLv3)
Classifier: Programming Language :: Python :: 3
Classifier: Programming Language :: Python :: 3.10
Classifier: Programming Language :: Python :: 3.11
Classifier: Programming Language :: Python :: 3.12
Classifier: Programming Language :: Python :: 3.13
Classifier: Topic :: Multimedia :: Sound/Audio
Classifier: Topic :: System :: System Shells
Project-URL: Homepage, https://github.com/thaim/rhythmdbctl
Project-URL: Repository, https://github.com/thaim/rhythmdbctl
